pyokapi
