Metadata-Version: 1.0
Name: pyokapi
Version: 0.0.3.2
Summary: RESTful API platform okapi python library
Home-page: http://www.okapi.pub/help/python
Author: okapi
Author-email: okapi@okapi.pub
License: http://www.okapi.pub/about.html
Platform: UNKNOWN
